nm510/__init__.py
nm510/nm510.py
nm510-0.0.3.dist-info/LICENSE
nm510-0.0.3.dist-info/METADATA
nm510-0.0.3.dist-info/WHEEL
nm510-0.0.3.dist-info/dependency_links.txt
nm510-0.0.3.dist-info/top_level.txt
nm510-0.0.3.dist-info/RECORD
