Metadata-Version: 2.1
Name: nm510
Version: 0.0.3
Summary: python package in development for TBD
Home-page: https://github.com/nathanmckinney/nm510
Author: Nathan McKinney
Author-email: mckinney@utk.edu
License: MIT license
Keywords: nm510
Platform: UNKNOWN
Classifier: Development Status :: 2 - Pre-Alpha
Classifier: Intended Audience :: Developers
Classifier: License :: OSI Approved :: MIT License
Classifier: Natural Language :: English
Classifier: Programming Language :: Python :: 3
Classifier: Programming Language :: Python :: 3.5
Classifier: Programming Language :: Python :: 3.6
Classifier: Programming Language :: Python :: 3.7
Classifier: Programming Language :: Python :: 3.8
Requires-Python: >=3.5
Requires-Dist: folium
Requires-Dist: ipyleaflet
